tixte/__init__.py
tixte/abc.py
tixte/client.py
tixte/config.py
tixte/delete.py
tixte/domain.py
tixte/enums.py
tixte/errors.py
tixte/file.py
tixte/http.py
tixte/permissions.py
tixte/state.py
tixte/upload.py
tixte/user.py
tixte/utils.py
tixte.py-1.0.3.dist-info/LICENSE
tixte.py-1.0.3.dist-info/METADATA
tixte.py-1.0.3.dist-info/WHEEL
tixte.py-1.0.3.dist-info/entry_points.txt
tixte.py-1.0.3.dist-info/top_level.txt
tixte.py-1.0.3.dist-info/RECORD
