Metadata-Version: 2.1
Name: tixte.py
Version: 1.0.3
Summary: The async wrapper for the Tixte API.
Home-page: https://github.com/NextChai/Tixte
Author: NextChai
License: MIT
Project-URL: Report a Bug, https://github.com/NextChai/Tixte/issues
Project-URL: Contribute, https://github.com/NextChai/Tixte/pulls
Classifier: License :: OSI Approved :: MIT License
Classifier: Programming Language :: Python :: 3.8
Classifier: Programming Language :: Python :: 3.9
License-File: LICENSE
Requires-Dist: aiohttp >=3.6.0
Provides-Extra: docs
Requires-Dist: sphinx ==4.4.0 ; extra == 'docs'
Requires-Dist: sphinxcontrib-trio ==1.1.2 ; extra == 'docs'
Requires-Dist: sphinxcontrib-websupport ; extra == 'docs'
Requires-Dist: typing-extensions ; extra == 'docs'
Provides-Extra: speed
Requires-Dist: orjson ; extra == 'speed'
Provides-Extra: test
Requires-Dist: pytest ; extra == 'test'
Requires-Dist: pytest-asyncio ; extra == 'test'
Requires-Dist: pytest-cov ; extra == 'test'
Requires-Dist: async-timeout ; extra == 'test'
